cubic_bezier_spline/__init__.py
cubic_bezier_spline/bezier_curve.py
cubic_bezier_spline/bezier_spline.py
cubic_bezier_spline/construct_splines.py
cubic_bezier_spline/control_point_casting.py
cubic_bezier_spline/curve_length.py
cubic_bezier_spline/matrices.py
cubic_bezier_spline/other_solvers.py
cubic_bezier_spline/pairwise.py
cubic_bezier_spline/py.typed
cubic_bezier_spline-0.19.1.dist-info/METADATA
cubic_bezier_spline-0.19.1.dist-info/WHEEL
cubic_bezier_spline-0.19.1.dist-info/top_level.txt
cubic_bezier_spline-0.19.1.dist-info/RECORD
