Metadata-Version: 2.4
Name: cubic_bezier_spline
Version: 0.19.1
Summary: Approximate or interpolate a sequence of points into a sequence of c2-continuous, non-rational cubic Bézier curves.
Author-email: Shay Hill <shay_public@hotmail.com>
License: MIT
Requires-Python: >=3.9
Requires-Dist: numpy
Requires-Dist: paragraphs
Requires-Dist: typing-extensions
Requires-Dist: vec2_math
Requires-Dist: svg_path_data
Provides-Extra: dev
Requires-Dist: pytest; extra == "dev"
Requires-Dist: pre-commit; extra == "dev"
Requires-Dist: commitizen; extra == "dev"
Requires-Dist: tox; extra == "dev"
